	<NpcDefinition>
		<CombatLevel>21</CombatLevel>
		<Examine>Animated steel armour.</Examine>
		<Bonus0>10</Bonus0>
		<Bonus1>10</Bonus1>
		<Bonus2>10</Bonus2>
		<Bonus3>10</Bonus3>
		<Bonus4>10</Bonus4>
		<Bonus5>4</Bonus5>
		<Bonus6>10</Bonus6>
		<Bonus7>10</Bonus7>
		<Bonus8>10</Bonus8>
		<Bonus9>10</Bonus9>
		<Bonus10>10</Bonus10>
		<Bonus11>22</Bonus11>
		<Bonus12>2</Bonus12>
		<Bonus13>3</Bonus13>
		<LifePoints>400</LifePoints>
		<Respawn>20</Respawn>
          <AttackAnimation>386</AttackAnimation>
          <DefenceAnimation>388</DefenceAnimation>
          <DeathAnimation>4167</DeathAnimation>
		<StrengthLevel>32</StrengthLevel>
		<AttackLevel>32</AttackLevel>
		<DefenceLevel>32</DefenceLevel>
		<RangeLevel>1</RangeLevel>
		<MagicLevel>1</MagicLevel>
		<AttackSpeed>5</AttackSpeed>
		<StartGraphics>-1</StartGraphics>
		<ProjectileId>-1</ProjectileId>
		<EndGraphics>-1</EndGraphics>
		<UsingMelee>true</UsingMelee>
		<UsingRange>false</UsingRange>
		<UsingMagic>false</UsingMagic>
		<Aggressive>false</Aggressive>
		<PoisonImmune>false</PoisonImmune>
	</NpcDefinition>
