	<NpcDefinition>
		<CombatLevel>99</CombatLevel>
		<Examine>It didn't get that big eating flies!</Examine>
		<Bonus0>10</Bonus0>
		<Bonus1>10</Bonus1>
		<Bonus2>10</Bonus2>
		<Bonus3>10</Bonus3>
		<Bonus4>10</Bonus4>
		<Bonus5>10</Bonus5>
		<Bonus6>10</Bonus6>
		<Bonus7>1</Bonus7>
		<Bonus8>10</Bonus8>
		<Bonus9>10</Bonus9>
		<Bonus10>10</Bonus10>
		<Bonus11>37</Bonus11>
		<Bonus12>0</Bonus12>
		<Bonus13>0</Bonus13>
		<LifePoints>1000</LifePoints>
		<Respawn>17</Respawn>
          <AttackAnimation>1793</AttackAnimation>
          <DefenceAnimation>1794</DefenceAnimation>
          <DeathAnimation>1795</DeathAnimation>
		<StrengthLevel>45</StrengthLevel>
		<AttackLevel>45</AttackLevel>
		<DefenceLevel>60</DefenceLevel>
		<RangeLevel>1</RangeLevel>
		<MagicLevel>1</MagicLevel>
		<AttackSpeed>6</AttackSpeed>
		<StartGraphics>-1</StartGraphics>
		<ProjectileId>-1</ProjectileId>
		<EndGraphics>-1</EndGraphics>
		<UsingMelee>true</UsingMelee>
		<UsingRange>false</UsingRange>
		<UsingMagic>false</UsingMagic>
		<Aggressive>false</Aggressive>
		<PoisonImmune>false</PoisonImmune>
	</NpcDefinition>
